pyberry/__init__.py
pyberry/datadict.py
pyberry/temp_tests.py
pymelon/__init__.py
pymelon/datadict.py
pymelon/temp_tests.py
pymelon-0.4.0.dist-info/METADATA
pymelon-0.4.0.dist-info/WHEEL
pymelon-0.4.0.dist-info/top_level.txt
pymelon-0.4.0.dist-info/RECORD
