Metadata-Version: 2.1
Name: pymelon
Version: 0.4.0
Summary: A data manipulation library for JSON and lists of dictionaries.
Home-page: https://github.com/jaz-alli/pymelon
Author: Jaz Allibhai
Author-email: jaz.allibhai@gmail.com
License: MIT
